JavaXunijiDicengYuanliZhishiZongjie/README.md
JavaXunijiDicengYuanliZhishiZongjie/__init__.py
JavaXunijiDicengYuanliZhishiZongjie/__main__.py
JavaXunijiDicengYuanliZhishiZongjie/file.epub
JavaXunijiDicengYuanliZhishiZongjie/index.html
JavaXunijiDicengYuanliZhishiZongjie/css/__init__.py
JavaXunijiDicengYuanliZhishiZongjie/css/annotations.css
JavaXunijiDicengYuanliZhishiZongjie/css/main.css
JavaXunijiDicengYuanliZhishiZongjie/css/normalize.css
JavaXunijiDicengYuanliZhishiZongjie/css/popup.css
JavaXunijiDicengYuanliZhishiZongjie/font/__init__.py
JavaXunijiDicengYuanliZhishiZongjie/font/fontello.eot
JavaXunijiDicengYuanliZhishiZongjie/font/fontello.svg
JavaXunijiDicengYuanliZhishiZongjie/font/fontello.ttf
JavaXunijiDicengYuanliZhishiZongjie/font/fontello.woff
JavaXunijiDicengYuanliZhishiZongjie/img/__init__.py
JavaXunijiDicengYuanliZhishiZongjie/img/annotator-glyph-sprite.png
JavaXunijiDicengYuanliZhishiZongjie/img/annotator-icon-sprite.png
JavaXunijiDicengYuanliZhishiZongjie/img/apple-touch-icon.png
JavaXunijiDicengYuanliZhishiZongjie/img/cancelfullscreen.png
JavaXunijiDicengYuanliZhishiZongjie/img/close.png
JavaXunijiDicengYuanliZhishiZongjie/img/fullscreen.png
JavaXunijiDicengYuanliZhishiZongjie/img/loader.gif
JavaXunijiDicengYuanliZhishiZongjie/img/menu-icon.png
JavaXunijiDicengYuanliZhishiZongjie/img/save.png
JavaXunijiDicengYuanliZhishiZongjie/img/saved.png
JavaXunijiDicengYuanliZhishiZongjie/img/settings-s.png
JavaXunijiDicengYuanliZhishiZongjie/img/settings.png
JavaXunijiDicengYuanliZhishiZongjie/img/star.png
JavaXunijiDicengYuanliZhishiZongjie/js/__init__.py
JavaXunijiDicengYuanliZhishiZongjie/js/epub.js
JavaXunijiDicengYuanliZhishiZongjie/js/epub.min.js
JavaXunijiDicengYuanliZhishiZongjie/js/epub.min.map
JavaXunijiDicengYuanliZhishiZongjie/js/hooks.min.js
JavaXunijiDicengYuanliZhishiZongjie/js/hooks.min.map
JavaXunijiDicengYuanliZhishiZongjie/js/reader.js
JavaXunijiDicengYuanliZhishiZongjie/js/reader.js.map
JavaXunijiDicengYuanliZhishiZongjie/js/reader.min.js
java_xuniji_diceng_yuanli_zhishi_zongjie-2024.3.5.0.dist-info/METADATA
java_xuniji_diceng_yuanli_zhishi_zongjie-2024.3.5.0.dist-info/WHEEL
java_xuniji_diceng_yuanli_zhishi_zongjie-2024.3.5.0.dist-info/entry_points.txt
java_xuniji_diceng_yuanli_zhishi_zongjie-2024.3.5.0.dist-info/top_level.txt
java_xuniji_diceng_yuanli_zhishi_zongjie-2024.3.5.0.dist-info/RECORD
